BetterPythonLogger/Logger.py
BetterPythonLogger/NoLoggerException.py
BetterPythonLogger/__init__.py
BetterPythonLogger-1.1.3.dist-info/LICENSE
BetterPythonLogger-1.1.3.dist-info/METADATA
BetterPythonLogger-1.1.3.dist-info/WHEEL
BetterPythonLogger-1.1.3.dist-info/top_level.txt
BetterPythonLogger-1.1.3.dist-info/RECORD
