Metadata-Version: 2.1
Name: BetterPythonLogger
Version: 1.1.3
Summary: A better, simple logger for python
Author-email: Scorval <thomas_cerqueira@yahoo.fr>
Project-URL: Homepage, https://github.com/thomascerqueira/BetterPythonLogger
Project-URL: Issues, https://github.com/thomascerqueira/BetterPythonLogger/issues
Project-URL: Changelog, https://github.com/thomascerqueira/BetterPythonLogger/blob/main/CHANGELOG.md
Classifier: Programming Language :: Python :: 3
Classifier: License :: OSI Approved :: MIT License
Classifier: Operating System :: OS Independent
Requires-Python: >=3.12
License-File: LICENSE
